[
  {
    "url": "https://risbar.kz/product/a1001-cat55e/",
    "title": "A1001-CAT5/5E",
    "description": "Описание A1001-CAT5/5E — разъём кат. 5/5e RJ45. Разъем RJ45, чистая медь, 8P8C, позолоченный обжимной сетевой разъем 24K. > Модульный сетевой разъем RJ45 для UTP Cat5,Cat5e. > Цвет:прозрачный > Вес: 1,4 г",
    "details": "Производитель: TaverLab | Наименование: <h3>A1001-CAT5/5E</h3> | Партномер: <h3>A1001-CAT5/5E</h3>",
    "category": "Разъёмы RJ45",
    "article": "",
    "availability": "Наличие:В наличии",
    "images": [
      "https://risbar.kz/wp-content/uploads/product/a1001-cat55e-1.png"
    ],
    "price": "0"
  },
  {
    "url": "https://risbar.kz/product/a1002-cat55e/",
    "title": "A1002-CAT5/5E",
    "description": "Описание A1002-CAT5/5E — разъём экранированный кат. 5/5e RJ45. Разъем экранированный RJ45, чистая медь, 8P8C, позолоченный обжимной сетевой разъем. > Модульный сетевой разъем RJ45 для UTP Cat5,Cat5e. > Позолоченные выводы для лучшей передачи данных и более высокого уровня сигнала > Цвет:прозрачный > Вес: 2.5 г",
    "details": "Производитель: TaverLab | Наименование: <h3>A1002-CAT5/5E</h3> | Партномер: <h3>A1002-CAT5/5E</h3>",
    "category": "Разъёмы RJ45",
    "article": "",
    "availability": "Наличие:В наличии",
    "images": [
      "https://risbar.kz/wp-content/uploads/product/a1002-cat55e-1.png"
    ],
    "price": "0"
  },
  {
    "url": "https://risbar.kz/product/a1002-cat6/",
    "title": "A1002-CAT6",
    "description": "Описание A1002-CAT6 — разъём экранированный кат. 6/6e RJ45. Разъем экранированный RJ45, чистая медь, 8P8C, позолоченный обжимной сетевой разъем. > Модульный сетевой разъем RJ45 для UTP Cat6. > Позолоченные выводы для лучшей передачи данных и более высокого уровня сигнала > Цвет:прозрачный > Вес: 2.5 г",
    "details": "Производитель: TaverLab | Наименование: <h3>A1002-CAT6</h3> | Партномер: <h3>A1002-CAT6</h3>",
    "category": "Разъёмы RJ45",
    "article": "",
    "availability": "Наличие:В наличии",
    "images": [
      "https://risbar.kz/wp-content/uploads/product/a1002-cat6-1.png"
    ],
    "price": "0"
  }
]